pythonSmallToolsByHanXu/__init__.py
pythonSmallToolsByHanXu/normalize_md/__init__.py
pythonSmallToolsByHanXu/rename_files/__init__.py
pythonSmallToolsByHanXu-1.1.0.dist-info/LICENSE
pythonSmallToolsByHanXu-1.1.0.dist-info/METADATA
pythonSmallToolsByHanXu-1.1.0.dist-info/WHEEL
pythonSmallToolsByHanXu-1.1.0.dist-info/top_level.txt
pythonSmallToolsByHanXu-1.1.0.dist-info/RECORD
